python_tutorial/Area_Fig.py
python_tutorial/__init__.py
AreaOfFigs-0.0.1.dist-info/LICENSE
AreaOfFigs-0.0.1.dist-info/METADATA
AreaOfFigs-0.0.1.dist-info/WHEEL
AreaOfFigs-0.0.1.dist-info/top_level.txt
AreaOfFigs-0.0.1.dist-info/RECORD
