Metadata-Version: 2.1
Name: AreaOfFigs
Version: 0.0.1
Summary: PythonTutorial
Home-page: UNKNOWN
Author: Developer Gautam
Author-email: developergautam07@gmail.com
License: UNKNOWN
Keywords: python,tutorial,area of figs,area,developergautam
Platform: UNKNOWN
Classifier: Development Status :: 1 - Planning
Classifier: Intended Audience :: Developers
Classifier: Programming Language :: Python :: 3
Classifier: Operating System :: Unix
Classifier: Operating System :: MacOS :: MacOS X
Classifier: Operating System :: Microsoft :: Windows
